datadrop/__init__.py
datadrop/cli.py
datadrop/datadrop.py
datadrop-0.1.0.dist-info/DESCRIPTION.rst
datadrop-0.1.0.dist-info/METADATA
datadrop-0.1.0.dist-info/RECORD
datadrop-0.1.0.dist-info/WHEEL
datadrop-0.1.0.dist-info/entry_points.txt
datadrop-0.1.0.dist-info/metadata.json
datadrop-0.1.0.dist-info/top_level.txt
