Metadata-Version: 2.0
Name: datadrop
Version: 0.1.0
Summary: flexible data artifact management plugin for source control.
Home-page: https://github.com/huntzhan/datadrop
Author: Hunt Zhan
Author-email: huntzhan.dev@gmail.com
License: MIT license
Keywords: datadrop
Platform: UNKNOWN
Classifier: Development Status :: 2 - Pre-Alpha
Classifier: Intended Audience :: Developers
Classifier: License :: OSI Approved :: MIT License
Classifier: Natural Language :: English
Classifier: Programming Language :: Python :: 2
Classifier: Programming Language :: Python :: 2.7
Classifier: Programming Language :: Python :: 3
Classifier: Programming Language :: Python :: 3.4
Classifier: Programming Language :: Python :: 3.5
Classifier: Programming Language :: Python :: 3.6
Requires-Dist: Click (>=6.0)
